{
  "MetaData": {
    "Schema": {
      "ManagerName": "AddonSchemaManager",
      "UId": "bb5382c0-62bd-4866-8919-be7f55c68619",
      "A2": "UsrRealtyBusinessRule",
      "A5": "5bb12f92-1df1-49bc-b65f-3044496af87a",
      "B1": [],
      "B2": [],
      "B3": [],
      "B6": "be3639ff-0c73-4f96-a9ac-03ed8907b896",
      "B8": "8.2.3.1351",
      "AD1": "40555dc5-49ae-4fbf-993e-cfb591d3f286",
      "AD2": "EntitySchemaManager",
      "AD3": "BusinessRule",
      "AD5": "3a2d6f51-1bfc-4c17-aacb-b53de4866b7c",
      "AD4": {
        "JI0": "Terrasoft.Core.BusinessRules.BusinessRules",
        "BRS1": [
          {
            "JI0": "Terrasoft.Core.BusinessRules.BusinessRule",
            "UId": "f5f023bc-5c05-9996-53d9-a42d67c17a96",
            "BR1": [
              {
                "JI0": "Terrasoft.Core.BusinessRules.Models.BusinessRuleCase",
                "UId": "8f2169ad-54ce-32b3-ead5-fa9b3bae2c19",
                "BRC2": [
                  {
                    "JI0": "Terrasoft.Core.BusinessRules.Models.Actions.BusinessRuleActionSetFilter",
                    "UId": "e605e69a-8fc1-04eb-651c-420490f12c86",
                    "BRA2": {
                      "JI0": "Terrasoft.Core.BusinessRules.Models.Expressions.BusinessRuleAttributeExpression",
                      "UId": "5aa7a241-7269-a505-b906-e3de40c287e8",
                      "BRX1": "UsrManager"
                    },
                    "BRA3": {
                      "JI0": "Terrasoft.Core.BusinessRules.Models.Expressions.BusinessRuleValueExpression",
                      "UId": "aed976f1-3ed0-7bc8-590d-b737c8b4823c",
                      "BVE1": "{\"items\":{\"276b5849-5712-451f-b8ec-e1cae2372f46\":{\"filterType\":4,\"comparisonType\":3,\"isEnabled\":true,\"trimDateTimeParameterToDate\":false,\"leftExpression\":{\"expressionType\":0,\"columnPath\":\"Type\"},\"isAggregative\":false,\"dataValueType\":10,\"referenceSchemaName\":\"ContactType\",\"rightExpressions\":[{\"expressionType\":2,\"parameter\":{\"dataValueType\":10,\"value\":{\"Name\":\"Employee\",\"Id\":\"60733efc-f36b-1410-a883-16d83cab0980\",\"value\":\"60733efc-f36b-1410-a883-16d83cab0980\",\"displayValue\":\"Employee\"}}}]}},\"logicalOperation\":0,\"isEnabled\":true,\"filterType\":6,\"rootSchemaName\":\"Contact\"}"
                    }
                  }
                ]
              }
            ],
            "BR2": [
              {
                "JI0": "Terrasoft.Core.BusinessRules.Models.Trigger",
                "UId": "aed32dfa-b6dc-7666-ad43-001d19d218e2",
                "BRT2": 2
              }
            ],
            "BR3": "BusinessRule_ef0b8f2"
          },
          {
            "JI0": "Terrasoft.Core.BusinessRules.BusinessRule",
            "UId": "57de750b-8090-27d5-2fb4-c888ef077456",
            "BR1": [
              {
                "JI0": "Terrasoft.Core.BusinessRules.Models.BusinessRuleCase",
                "UId": "59dea6f9-4b72-960c-e199-40df0a9466ab",
                "BRC2": [
                  {
                    "JI0": "Terrasoft.Core.BusinessRules.Models.Actions.BusinessRuleActionFilterLookup",
                    "UId": "8b0e9206-63ee-760e-fdfe-a61efd045114",
                    "BRA2": {
                      "JI0": "Terrasoft.Core.BusinessRules.Models.Expressions.BusinessRuleAttributeExpression",
                      "UId": "b6775b99-fc5f-4ff1-9ce7-be62c60770e1"
                    },
                    "BRA3": {
                      "JI0": "Terrasoft.Core.BusinessRules.Models.Expressions.BusinessRuleValueExpression",
                      "UId": "0590ca87-ecff-4079-8f3c-ea5ad8315074"
                    },
                    "BSFL1": {
                      "JI0": "Terrasoft.Core.BusinessRules.Models.Expressions.BusinessRuleFilterLookupExpression",
                      "UId": "e157c593-776f-ea28-966f-28b4395295c7",
                      "BRE1": "Lookup",
                      "BRE3": "City",
                      "BVP1": "UsrCity",
                      "BVF1": "Country"
                    },
                    "BSFR1": {
                      "JI0": "Terrasoft.Core.BusinessRules.Models.Expressions.BusinessRuleFilterLookupExpression",
                      "UId": "df5cdfec-830b-e943-18fb-de3c11ed29a7",
                      "BRE1": "Lookup",
                      "BRE3": "Country",
                      "BVP1": "UsrCountry",
                      "BVF1": "null"
                    }
                  }
                ]
              }
            ],
            "BR2": [
              {
                "JI0": "Terrasoft.Core.BusinessRules.Models.Trigger",
                "UId": "b30f82ea-c465-80b3-1507-06b927449bb5",
                "BRT2": 2
              },
              {
                "JI0": "Terrasoft.Core.BusinessRules.Models.Trigger",
                "UId": "93f5c126-83f0-16d8-63b0-3707b7489d2d",
                "BRT1": "UsrCountry"
              }
            ],
            "BR3": "BusinessRule_3d34e9e"
          },
          {
            "JI0": "Terrasoft.Core.BusinessRules.BusinessRule",
            "UId": "6d64bec8-e1d1-c59c-96b3-1a5d144c298e",
            "BR1": [
              {
                "JI0": "Terrasoft.Core.BusinessRules.Models.BusinessRuleCase",
                "UId": "9735ace3-b92f-38e3-90ca-b6d24340975c",
                "BRC1": {
                  "JI0": "Terrasoft.Core.BusinessRules.Models.Conditions.BusinessRuleCondition",
                  "UId": "492dfe57-46d2-60bd-c22c-967a949c609a",
                  "BCO1": {
                    "JI0": "Terrasoft.Core.BusinessRules.Models.Expressions.BusinessRuleAttributeExpression",
                    "UId": "9191b183-6333-8b76-ae1f-1656383f9f2b",
                    "BRE2": "AttributeValue",
                    "BRX1": "UsrCountry"
                  },
                  "BCO2": {
                    "JI0": "Terrasoft.Core.BusinessRules.Models.Expressions.BusinessRuleAttributeExpression",
                    "UId": "342fc6aa-65ef-0022-bdac-df778520ad82",
                    "BRE2": "AttributeValue",
                    "BRX1": "UsrCity.Country"
                  },
                  "BCO3": 3
                },
                "BRC2": [
                  {
                    "JI0": "Terrasoft.Core.BusinessRules.Models.Actions.BusinessRuleActionSetValues",
                    "UId": "96ce74a6-937a-0c16-943b-a29e4e0391cd",
                    "BRA2": {
                      "JI0": "Terrasoft.Core.BusinessRules.Models.Expressions.BusinessRuleAttributeExpression",
                      "UId": "9afb1cc2-41d2-487c-b963-39c75600c5c4"
                    },
                    "BRA3": {
                      "JI0": "Terrasoft.Core.BusinessRules.Models.Expressions.BusinessRuleValueExpression",
                      "UId": "e0be0166-8d08-43ed-8bdd-c986fcd6dd1b"
                    },
                    "BSVS1": [
                      {
                        "JI0": "Terrasoft.Core.BusinessRules.Models.Expressions.BusinessRuleSetValueItem",
                        "UId": "36496bf9-a8c1-26f6-6018-ad0927b08e71",
                        "BRA2": {
                          "JI0": "Terrasoft.Core.BusinessRules.Models.Expressions.BusinessRuleAttributeExpression",
                          "UId": "eb0626e2-3442-b60b-d3fa-8e608f59c001",
                          "BRE1": "Lookup",
                          "BRX1": "UsrCity",
                          "BRX2": "null"
                        },
                        "BRA3": {
                          "JI0": "Terrasoft.Core.BusinessRules.Models.Expressions.BusinessRuleEmptyValueExpression",
                          "UId": "6552ced4-9ea5-12be-2023-0ed81d85fda5",
                          "BRE1": "Lookup",
                          "BVE1": "00000000-0000-0000-0000-000000000000"
                        }
                      }
                    ]
                  }
                ]
              }
            ],
            "BR2": [
              {
                "JI0": "Terrasoft.Core.BusinessRules.Models.Trigger",
                "UId": "50b040c2-500b-9d05-7824-a6856a4d574d",
                "BRT1": "UsrCountry"
              }
            ],
            "BR3": "Autogenerated_57de750b-8090-27d5-2fb4-c888ef077456_ClearValue",
            "BR5": "57de750b-8090-27d5-2fb4-c888ef077456",
            "BR6": "8b0e9206-63ee-760e-fdfe-a61efd045114"
          },
          {
            "JI0": "Terrasoft.Core.BusinessRules.BusinessRule",
            "UId": "a9a0d5e6-f747-0488-fce0-de6363c015f4",
            "BR1": [
              {
                "JI0": "Terrasoft.Core.BusinessRules.Models.BusinessRuleCase",
                "UId": "c24d1a41-b6d5-87d7-52b7-a6145170e84c",
                "BRC1": {
                  "JI0": "Terrasoft.Core.BusinessRules.Models.Conditions.BusinessRuleCondition",
                  "UId": "06fe3497-cd04-d523-fcfb-4726a765ed96",
                  "BCO1": {
                    "JI0": "Terrasoft.Core.BusinessRules.Models.Expressions.BusinessRuleAttributeExpression",
                    "UId": "6eb8380c-87aa-5981-37fd-8b4a6ed83433",
                    "BRE2": "AttributeValue",
                    "BRX1": "UsrCity"
                  },
                  "BCO3": 1
                },
                "BRC2": [
                  {
                    "JI0": "Terrasoft.Core.BusinessRules.Models.Actions.BusinessRuleActionSetValues",
                    "UId": "53b1a6d5-7836-f8a0-4eb8-cef508993b78",
                    "BRA2": {
                      "JI0": "Terrasoft.Core.BusinessRules.Models.Expressions.BusinessRuleAttributeExpression",
                      "UId": "ccc90fd1-e6b6-4f4d-90f2-906bd089a620"
                    },
                    "BRA3": {
                      "JI0": "Terrasoft.Core.BusinessRules.Models.Expressions.BusinessRuleValueExpression",
                      "UId": "14a5d7ba-468c-4daa-ae52-1471d44939b3"
                    },
                    "BSVS1": [
                      {
                        "JI0": "Terrasoft.Core.BusinessRules.Models.Expressions.BusinessRuleSetValueItem",
                        "UId": "34d049ef-f14a-d359-47a6-b942b39341f5",
                        "BRA2": {
                          "JI0": "Terrasoft.Core.BusinessRules.Models.Expressions.BusinessRuleAttributeExpression",
                          "UId": "12a4f48a-c96a-32d6-ee6a-eb5c084fc7df",
                          "BRX1": "UsrCountry",
                          "BRX2": "null"
                        },
                        "BRA3": {
                          "JI0": "Terrasoft.Core.BusinessRules.Models.Expressions.BusinessRuleAttributeExpression",
                          "UId": "1cca46bf-d5c2-d702-9265-020245cd983b",
                          "BRE1": "Lookup",
                          "BRE2": "AttributeValue",
                          "BRE3": "Country",
                          "BRX1": "UsrCity.Country"
                        }
                      }
                    ]
                  }
                ]
              }
            ],
            "BR2": [
              {
                "JI0": "Terrasoft.Core.BusinessRules.Models.Trigger",
                "UId": "e6a0259d-92f0-f06b-1674-f3a187c6a30e",
                "BRT1": "UsrCity"
              }
            ],
            "BR3": "Autogenerated_57de750b-8090-27d5-2fb4-c888ef077456_PopulateValue",
            "BR5": "57de750b-8090-27d5-2fb4-c888ef077456",
            "BR6": "8b0e9206-63ee-760e-fdfe-a61efd045114"
          },
          {
            "JI0": "Terrasoft.Core.BusinessRules.BusinessRule",
            "UId": "101d022f-8bbc-3655-b147-d45113160bb7",
            "BR1": [
              {
                "JI0": "Terrasoft.Core.BusinessRules.Models.BusinessRuleCase",
                "UId": "4d9a7754-04b5-0c31-c052-c25fde968f0f",
                "BRC1": {
                  "JI0": "Terrasoft.Core.BusinessRules.Models.Conditions.BusinessRuleGroupCondition",
                  "UId": "36e13af9-7fc6-318b-9c41-538a0eea8846",
                  "BGC1": 1,
                  "BGC2": [
                    {
                      "JI0": "Terrasoft.Core.BusinessRules.Models.Conditions.BusinessRuleCondition",
                      "UId": "70d05eac-c5ba-c39c-ce9b-9ad2fba23eba",
                      "BCO1": {
                        "JI0": "Terrasoft.Core.BusinessRules.Models.Expressions.BusinessRuleSysValueExpression",
                        "UId": "3b136715-9297-94ce-6d17-48676e438307",
                        "BRE1": "ObjectList",
                        "BRE2": "SysValue",
                        "BSV1": "CurrentUserRoles"
                      },
                      "BCO2": {
                        "JI0": "Terrasoft.Core.BusinessRules.Models.Expressions.BusinessRuleValueExpression",
                        "UId": "f14ada89-7efa-21ca-f61e-8c9a8726c0f5",
                        "BRE1": "Lookup",
                        "BRE3": "SysAdminUnit",
                        "BVE1": "c31ba121-e394-4b7e-b7ea-d67e85c6f2dd"
                      },
                      "BCO3": 11
                    }
                  ]
                },
                "BRC2": [
                  {
                    "JI0": "Terrasoft.Core.BusinessRules.Models.Actions.BusinessRuleActionEditableElement",
                    "UId": "345fbf1a-e2db-9afa-f375-6a4c5f18e09c",
                    "BRA4": "UsrPrice"
                  }
                ]
              }
            ],
            "BR2": [
              {
                "JI0": "Terrasoft.Core.BusinessRules.Models.Trigger",
                "UId": "907fdb66-e377-4120-9b1e-783c1b33b21a",
                "BRT2": 2
              }
            ],
            "BR3": "BusinessRule_487decf"
          }
        ]
      }
    }
  }
}